cli_args_system/__init__.py
cli_args_system/args.py
cli_args_system/extras.py
cli_args_system/flags_content.py
cli_args_system/list_args.py
cli_args_system-1.3.dist-info/LICENSE.txt
cli_args_system-1.3.dist-info/METADATA
cli_args_system-1.3.dist-info/WHEEL
cli_args_system-1.3.dist-info/top_level.txt
cli_args_system-1.3.dist-info/RECORD
